.gitignore
LICENSE
README.md
setup.py
adafruit_micropython_register.egg-info/PKG-INFO
adafruit_micropython_register.egg-info/SOURCES.txt
adafruit_micropython_register.egg-info/dependency_links.txt
adafruit_micropython_register.egg-info/top_level.txt
adafruit_register/__init__.py
adafruit_register/i2c_bcd_datetime.py
adafruit_register/i2c_bit.py