Metadata-Version: 1.1
Name: adafruit-micropython-register
Version: 0.0.1
Summary: MicroPython data descriptor classes to represent hardware registers on I2C and SPI devices.
Home-page: https://github.com/adafruit/Adafruit_MicroPython_Register
Author: Adafruit Industries
Author-email: support@adafruit.com
License: MIT
Keywords: adafruit register micropython
Platform: UNKNOWN
Classifier: Development Status :: 3 - Alpha
Classifier: Intended Audience :: Developers
Classifier: Topic :: Software Development :: Libraries
Classifier: Topic :: System :: Hardware
Classifier: License :: OSI Approved :: MIT License
Classifier: Programming Language :: Python :: 3
Classifier: Programming Language :: Python :: 3.4
Classifier: Programming Language :: Python :: 3.5
